acts/__init__.py
acts/asserts.py
acts/base_test.py
acts/config_parser.py
acts/context.py
acts/dict_object.py
acts/error.py
acts/keys.py
acts/logger.py
acts/records.py
acts/signals.py
acts/test_decorators.py
acts/test_runner.py
acts/tracelogger.py
acts/utils.py
acts/bin/__init__.py
acts/bin/act.py
acts/bin/monsoon.py
acts/controllers/__init__.py
acts/controllers/abstract_inst.py
acts/controllers/access_point.py
acts/controllers/adb.py
acts/controllers/android_device.py
acts/controllers/arduino_wifi_dongle.py
acts/controllers/attenuator.py
acts/controllers/bluetooth_pts_device.py
acts/controllers/buds_controller.py
acts/controllers/cellular_simulator.py
acts/controllers/chameleon_controller.py
acts/controllers/fastboot.py
acts/controllers/fuchsia_device.py
acts/controllers/iperf_client.py
acts/controllers/iperf_server.py
acts/controllers/monsoon.py
acts/controllers/native.py
acts/controllers/native_android_device.py
acts/controllers/packet_capture.py
acts/controllers/packet_sender.py
acts/controllers/pdu.py
acts/controllers/relay_device_controller.py
acts/controllers/sniffer.py
acts/controllers/android_lib/__init__.py
acts/controllers/android_lib/android_api.py
acts/controllers/android_lib/errors.py
acts/controllers/android_lib/events.py
acts/controllers/android_lib/logcat.py
acts/controllers/android_lib/services.py
acts/controllers/anritsu_lib/__init__.py
acts/controllers/anritsu_lib/_anritsu_utils.py
acts/controllers/anritsu_lib/cell_configurations.py
acts/controllers/anritsu_lib/md8475_cellular_simulator.py
acts/controllers/anritsu_lib/md8475a.py
acts/controllers/anritsu_lib/mg3710a.py
acts/controllers/ap_lib/__init__.py
acts/controllers/ap_lib/ap_get_interface.py
acts/controllers/ap_lib/ap_iwconfig.py
acts/controllers/ap_lib/bridge_interface.py
acts/controllers/ap_lib/dhcp_config.py
acts/controllers/ap_lib/dhcp_server.py
acts/controllers/ap_lib/hostapd.py
acts/controllers/ap_lib/hostapd_ap_preset.py
acts/controllers/ap_lib/hostapd_bss_settings.py
acts-0.9.dist-info/METADATA
acts-0.9.dist-info/WHEEL
acts-0.9.dist-info/top_level.txt
acts-0.9.dist-info/RECORD
